outerport/__init__.py
outerport/client.py
outerport/models/component.py
outerport/models/core.py
outerport/models/document.py
outerport/models/folder.py
outerport/models/job_status.py
outerport/models/question.py
outerport/models/retention_policy.py
outerport/models/setting.py
outerport/resources/base_resource.py
outerport/resources/components.py
outerport/resources/documents.py
outerport/resources/folders.py
outerport/resources/job_statuses.py
outerport/resources/questions.py
outerport/resources/retention_policies.py
outerport/resources/settings.py
outerport-0.2.26.dist-info/METADATA
outerport-0.2.26.dist-info/WHEEL
outerport-0.2.26.dist-info/licenses/LICENSE
outerport-0.2.26.dist-info/RECORD
