Metadata-Version: 2.4
Name: outerport
Version: 0.2.26
Summary: Outerport Python SDK
Project-URL: Homepage, https://outerport.com
Project-URL: Documentation, https://docs.outerport.com
Author-email: "Outerport (Genban, Inc.)" <support@outerport.com>
License: Apache Software License
License-File: LICENSE
Keywords: api,outerport,sdk
Classifier: Development Status :: 4 - Beta
Classifier: Intended Audience :: Developers
Classifier: License :: OSI Approved :: Apache Software License
Classifier: Programming Language :: Python :: 3
Classifier: Programming Language :: Python :: 3.8
Classifier: Programming Language :: Python :: 3.9
Classifier: Programming Language :: Python :: 3.10
Classifier: Programming Language :: Python :: 3.11
Requires-Python: >=3.8
Requires-Dist: aiohttp>=3.10.11
Requires-Dist: pydantic>=2.10.6
Requires-Dist: requests>=2.32.3
Requires-Dist: sseclient>=0.0.27
